mcp_server_table/__init__.py
mcp_server_table/main.py
mcp_server_table/postinstall.py
servicenow_mcp-0.1.1.dist-info/METADATA
servicenow_mcp-0.1.1.dist-info/WHEEL
servicenow_mcp-0.1.1.dist-info/entry_points.txt
servicenow_mcp-0.1.1.dist-info/top_level.txt
servicenow_mcp-0.1.1.dist-info/RECORD
