Metadata-Version: 2.4
Name: servicenow-mcp
Version: 0.1.1
Summary: MCP for ServiceNow
Author-email: Veera <mallikarjun.servicenow@gmail.com>
License-Expression: MIT
Classifier: Programming Language :: Python :: 3
Classifier: Operating System :: OS Independent
Requires-Python: >=3.12
Requires-Dist: fastapi>=0.116.1
Requires-Dist: mcp[cli]>=1.12.0
Requires-Dist: uvicorn>=0.35.0
Requires-Dist: zeep>=4.3.1
Requires-Dist: platformdirs>=4.2.2
